worldcatidentities/__init__.py
worldcatidentities/authority.py
worldcatidentities-0.2.dist-info/LICENSE
worldcatidentities-0.2.dist-info/METADATA
worldcatidentities-0.2.dist-info/WHEEL
worldcatidentities-0.2.dist-info/top_level.txt
worldcatidentities-0.2.dist-info/RECORD
